eth_defi/__init__.py
eth_defi/aave_v2/constants.py
eth_defi/aave_v2/events.py
eth_defi/aave_v3/README.md
eth_defi/aave_v3/aave-hardhat-localhost-export.json
eth_defi/aave_v3/balances.py
eth_defi/aave_v3/constants.py
eth_defi/aave_v3/deployer.py
eth_defi/aave_v3/deployment.py
eth_defi/aave_v3/events.py
eth_defi/aave_v3/loan.py
eth_defi/aave_v3/rates.py
eth_defi/aave_v3/reserve.py
eth_defi/abi/1delta/AaveFlashModule.json
eth_defi/abi/1delta/AaveMarginTraderInit.json
eth_defi/abi/1delta/AddressStringUtil.json
eth_defi/abi/1delta/BalancerFlashModule.json
eth_defi/abi/1delta/BalancerFlashModuleV2.json
eth_defi/abi/1delta/BaseDecoder.json
eth_defi/abi/1delta/BaseLendingBroker.json
eth_defi/abi/1delta/BaseSwapper.json
eth_defi/abi/1delta/BlockTimestamp.json
eth_defi/abi/1delta/BytesLib.json
eth_defi/abi/1delta/CallbackValidation.json
eth_defi/abi/1delta/CometFlashAggregator.json
eth_defi/abi/1delta/CometManagementModule.json
eth_defi/abi/1delta/CometMarginTradeDataViewerModule.json
eth_defi/abi/1delta/CometMarginTraderInit.json
eth_defi/abi/1delta/CometMarginTraderModule.json
eth_defi/abi/1delta/CometMarginTrading.json
eth_defi/abi/1delta/CometMoneyMarketModule.json
eth_defi/abi/1delta/CometSweeperModule.json
eth_defi/abi/1delta/CometUniV3Callback.json
eth_defi/abi/1delta/ConfigModule.json
eth_defi/abi/1delta/Context.json
eth_defi/abi/1delta/DeltaBrokerProxy.json
eth_defi/abi/1delta/DeltaBrokerProxyLegacy.json
eth_defi/abi/1delta/DeltaFlashAggregator.json
eth_defi/abi/1delta/DeltaFlashAggregatorMantle.json
eth_defi/abi/1delta/EIP712.json
eth_defi/abi/1delta/ERC20.json
eth_defi/abi/1delta/FlashAggregator.json
eth_defi/abi/1delta/HexStrings.json
eth_defi/abi/1delta/IAccountInit.json
eth_defi/abi/1delta/IComet.json
eth_defi/abi/1delta/ICreditPermit.json
eth_defi/abi/1delta/IERC1271.json
eth_defi/abi/1delta/IERC165.json
eth_defi/abi/1delta/IERC173.json
eth_defi/abi/1delta/IERC20.json
eth_defi/abi/1delta/IERC20Balance.json
eth_defi/abi/1delta/IERC20Metadata.json
web3_ethereum_defi-0.31.dist-info/LICENSE.txt
web3_ethereum_defi-0.31.dist-info/METADATA
web3_ethereum_defi-0.31.dist-info/WHEEL
web3_ethereum_defi-0.31.dist-info/entry_points.txt
web3_ethereum_defi-0.31.dist-info/RECORD
