Metadata-Version: 2.3
Name: web3-ethereum-defi
Version: 0.31
Summary: Python library for Uniswap, Aave, ChainLink, Enzyme and other protocols on BNB Chain, Polygon, Ethereum and other blockchains
License: MIT
Keywords: uniswap,aave,gmx,safe,ethereum,cryptocurrency,erc-20,pancakeswap,bnb smart chain,base,web3,blockchain,avalanche,arbitrum,chainlink
Author: Mikko Ohtamaa
Author-email: mikko@tradingstrategy.ai
Requires-Python: >=3.10,<4
Classifier: License :: OSI Approved :: MIT License
Classifier: Programming Language :: Python :: 3
Classifier: Programming Language :: Python :: 3.10
Classifier: Programming Language :: Python :: 3.11
Classifier: Programming Language :: Python :: 3.12
Classifier: Programming Language :: Python :: 3.13
Provides-Extra: data
Provides-Extra: docs
Provides-Extra: hypersync
Provides-Extra: test
Requires-Dist: Sphinx (>=4.5.0,<5.0.0) ; extra == "docs"
Requires-Dist: cachetools (>=4)
Requires-Dist: eth-bloom (>=2.0.0,<3.0.0)
Requires-Dist: eth-pydantic-types (<0.2)
Requires-Dist: evm-trace (>=0.1.0a17,<0.2.0)
Requires-Dist: furo (>=2022.6.4.1,<2023.0.0.0) ; extra == "docs"
Requires-Dist: futureproof (>=0.3.1,<0.4.0)
Requires-Dist: gmx-python-ng (==1.0.1)
Requires-Dist: gql[requests] (>=3.3.0,<4.0.0) ; extra == "data"
Requires-Dist: hypersync (>=0.8.5,<0.9.0) ; extra == "hypersync"
Requires-Dist: joblib (>=1.4.2,<2.0.0)
Requires-Dist: jupyter (>=1.0.0,<2.0.0) ; extra == "data"
Requires-Dist: matplotlib (>=3.5) ; extra == "data"
Requires-Dist: multicall (>=0.9.0,<0.10.0)
Requires-Dist: nbsphinx (>=0.8.9,<0.9.0) ; extra == "docs"
Requires-Dist: numpy (<2) ; extra == "data"
Requires-Dist: pandas (>=1.4) ; extra == "data"
Requires-Dist: plotly (>=5.8.2) ; extra == "data"
Requires-Dist: psutil (>=5.9.0,<6.0.0)
Requires-Dist: pyarrow ; extra == "data"
Requires-Dist: pytest-xdist (>=3.3.1,<4.0.0) ; extra == "test"
Requires-Dist: pytz (>=2024.2,<2025.0)
Requires-Dist: safe-eth-py (==6.0.0b42)
Requires-Dist: setuptools (>=63,<=70)
Requires-Dist: sigfig (>=1.3.2,<2.0.0)
Requires-Dist: sphinx-autodoc-typehints (>=1.16.0,<2.0.0) ; extra == "docs"
Requires-Dist: sphinx-rtd-theme (>=1.0.0,<2.0.0) ; extra == "docs" or extra == "docs"
Requires-Dist: sphinx-sitemap (>=2.2.0,<3.0.0) ; extra == "docs" or extra == "docs"
Requires-Dist: tenacity ; extra == "data"
Requires-Dist: tqdm (>=4.66.1) ; extra == "data"
Requires-Dist: tqdm-loggable (>=0.1.3)
Requires-Dist: ujson (>=5.8.0)
Requires-Dist: urllib3 (>=2)
Requires-Dist: web3-google-hsm (>=0.1.0,<0.2.0)
Requires-Dist: web3[tester] (==6.14.0)
Requires-Dist: zope-dottedname (>=6.0,<7.0) ; extra == "docs"
Project-URL: Changelog, https://github.com/tradingstrategy-ai/web3-ethereum-defi/blob/master/CHANGELOG.md
Project-URL: Documentation, https://web3-ethereum-defi.readthedocs.io/
Project-URL: Discord, https://discord.gg/5M88m9nM8H
Project-URL: Homepage, https://web3-ethereum-defi.readthedocs.io/
Project-URL: Repository, https://github.com/tradingstrategy-ai/web3-ethereum-defi
Project-URL: Sponsor, https://tradingstrategy.ai
Project-URL: Twitter, https://twitter.com/tradingprotocol
Project-URL: Youtube, https://www.youtube.com/@tradingstrategyprotocol
